dm_job_lib/__init__.py
dm_job_lib/loader.py
dm_job_lib/utils.py
dm_job_lib-0.0.50.dist-info/LICENSE
dm_job_lib-0.0.50.dist-info/METADATA
dm_job_lib-0.0.50.dist-info/WHEEL
dm_job_lib-0.0.50.dist-info/top_level.txt
dm_job_lib-0.0.50.dist-info/RECORD
