Metadata-Version: 2.1
Name: dm-job-lib
Version: 0.0.50
Summary: Data Manager Job Library
Home-page: https://github.com/stonezhong/DataManager/tree/master/client/dm_job_lib
Author: Stone Zhong
Author-email: stonezhong@hotmail.com
License: MIT
Platform: UNKNOWN
Classifier: License :: OSI Approved :: MIT License
Classifier: Programming Language :: Python :: 3
Requires-Dist: dc-client
